pactio/__init__.py
pactio/decorators.py
pactio/middleware.py
pactio/utils.py
pactio-0.0.4.dist-info/LICENSE
pactio-0.0.4.dist-info/METADATA
pactio-0.0.4.dist-info/WHEEL
pactio-0.0.4.dist-info/top_level.txt
pactio-0.0.4.dist-info/RECORD
