Metadata-Version: 2.1
Name: pactio
Version: 0.0.4
Requires-Python: >=3.11
License-File: LICENSE
Requires-Dist: Django>=5
Requires-Dist: pydantic>=2.8
